Metadata-Version: 2.1
Name: smommit
Version: 0.1.1
Summary: The CLI tool for forgetful gits.
Home-page: https://github.com/andygello555/smommit
Author: Jakab Zeller
Author-email: jakabzeller0@gmail.com
License: UNKNOWN
Platform: UNKNOWN
Classifier: Programming Language :: Python :: 3
Classifier: License :: OSI Approved :: MIT License
Classifier: Operating System :: OS Independent
Requires-Python: >=3
